mcp_play_windows_sound/__init__.py
mcp_play_windows_sound/__main__.py
mcp_play_windows_sound/server.py
mcp_play_windows_sound-0.4.6.dist-info/METADATA
mcp_play_windows_sound-0.4.6.dist-info/WHEEL
mcp_play_windows_sound-0.4.6.dist-info/entry_points.txt
mcp_play_windows_sound-0.4.6.dist-info/RECORD
