Metadata-Version: 2.4
Name: mcp-play-windows-sound
Version: 0.4.6
Summary: Model Context Protocol server for playing Windows system sounds
Project-URL: Homepage, https://github.com/avram0korets0kornit/mcp-servers
Project-URL: Bug Tracker, https://github.com/avram0korets0kornit/mcp-servers/issues
Author: MCP Contributors
Classifier: License :: OSI Approved :: MIT License
Classifier: Operating System :: OS Independent
Classifier: Programming Language :: Python :: 3
Requires-Python: >=3.10
Requires-Dist: mcp>=1.0.0
Requires-Dist: pydantic>=2.0.0
